autographs/__init__.py
autographs/faces/__init__.py
autographs/faces/halfedge.py
autographs-0.0.4.dist-info/METADATA
autographs-0.0.4.dist-info/RECORD
autographs-0.0.4.dist-info/WHEEL
autographs-0.0.4.dist-info/top_level.txt
