Metadata-Version: 2.1
Name: autographs
Version: 0.0.4
Summary: A collection of tools to make graph stuff easy.
Home-page: https://github.com/gerrymandr/autographs
Author: Metric Geometry and Gerrymandering Group
Author-email: gerrymandr@gmail.com
License: UNKNOWN
Platform: UNKNOWN
Requires-Dist: numpy
Requires-Dist: pysal
Requires-Dist: matplotlib
Requires-Dist: geopandas
Requires-Dist: matplotlib-label-lines
